cava/CAVA.py
cava/CHANGELOG
cava/EnsemblDB.py
cava/MANE.py
cava/RefSeqDB.py
cava/VERSION
cava/__init__.py
cava/dbSNPDB.py
cava/data/cava_db.GRCh38.MANE.sorted.gz
cava/data/cava_db.GRCh38.MANE.sorted.gz.tbi
cava/data/cava_db.GRCh38.MANE.sorted.txt
cava/ensembldb/README.md
cava/ensembldb/__init__.py
cava/ensembldb/customdb_prep.py
cava/ensembldb/main.py
cava/ensembldb/main_refseq.py
cava/ensembldb/mane_db_prep.py
cava/test/CustomTX.txt
cava/test/CustomTX2.txt
cava/test/test.sh
cava/test/test_csn.py
cava/test/test_end2end.py
cava/utils/__init__.py
cava/utils/conseq.py
cava/utils/core.py
cava/utils/csn.py
cava/utils/data.py
cava/utils/helper.py
cava/utils/main.py
CAVA-2.0.7.dist-info/LICENCE
CAVA-2.0.7.dist-info/METADATA
CAVA-2.0.7.dist-info/WHEEL
CAVA-2.0.7.dist-info/top_level.txt
CAVA-2.0.7.dist-info/RECORD
